elphick/mass_composition/__init__.py
elphick/mass_composition/balance.py
elphick/mass_composition/config/__init__.py
elphick/mass_composition/config/config_read.py
elphick/mass_composition/config/flowsheet_example.yaml
elphick/mass_composition/config/mc_config.yml
elphick/mass_composition/dag.py
elphick/mass_composition/datasets/__init__.py
elphick/mass_composition/datasets/datasets.py
elphick/mass_composition/datasets/downloader.py
elphick/mass_composition/datasets/register.csv
elphick/mass_composition/datasets/sample_data.py
elphick/mass_composition/flowsheet.py
elphick/mass_composition/layout.py
elphick/mass_composition/mass_composition.py
elphick/mass_composition/mc_node.py
elphick/mass_composition/mc_status.py
elphick/mass_composition/mc_xarray.py
elphick/mass_composition/plot.py
elphick/mass_composition/stream.py
elphick/mass_composition/utils/__init__.py
elphick/mass_composition/utils/amenability.py
elphick/mass_composition/utils/components.py
elphick/mass_composition/utils/geometry.py
elphick/mass_composition/utils/hash_utils.py
elphick/mass_composition/utils/interp.py
elphick/mass_composition/utils/loader.py
elphick/mass_composition/utils/moisture.py
elphick/mass_composition/utils/parallel.py
elphick/mass_composition/utils/partition.py
elphick/mass_composition/utils/pd_utils.py
elphick/mass_composition/utils/sampling.py
elphick/mass_composition/utils/size.py
elphick/mass_composition/utils/size_distribution.py
elphick/mass_composition/utils/sklearn.py
elphick/mass_composition/utils/viz.py
elphick/mass_composition/variables.py
mass_composition-0.6.8.dist-info/LICENSE
mass_composition-0.6.8.dist-info/METADATA
mass_composition-0.6.8.dist-info/WHEEL
mass_composition-0.6.8.dist-info/entry_points.txt
mass_composition-0.6.8.dist-info/RECORD
