Metadata-Version: 2.1
Name: mass-composition
Version: 0.6.8
Summary: For managing multi-dimensional mass-composition datasets, supporting weighted mathematical operations and visualisation.
Home-page: https://github.com/elphick/mass-composition
Author: Greg
Author-email: greg@elphick.com.au
Requires-Python: >=3.9,<3.12
Classifier: Programming Language :: Python :: 3
Classifier: Programming Language :: Python :: 3.9
Classifier: Programming Language :: Python :: 3.10
Classifier: Programming Language :: Python :: 3.11
Provides-Extra: estimation
Provides-Extra: network
Provides-Extra: viz
Requires-Dist: joblib (>=1.4.0,<2.0.0) ; extra == "network"
Requires-Dist: jsonpickle (>=3.0.1)
Requires-Dist: kaleido (==0.2.1) ; extra == "viz"
Requires-Dist: matplotlib (>=3.3,<4.0)
Requires-Dist: networkx (>2.0,<4.0) ; extra == "network"
Requires-Dist: periodictable (>=1.6.1,<2.0.0)
Requires-Dist: plotly (>=5.3,<6.0)
Requires-Dist: pooch (>=1.7.0,<2.0.0)
Requires-Dist: pyyaml (>=6.0,<7.0)
Requires-Dist: scikit-learn (>=1.0) ; extra == "estimation"
Requires-Dist: scipy (>=1.9.0,<2.0.0)
Requires-Dist: seaborn (>0.11)
Requires-Dist: statsmodels (>=0.14.0) ; extra == "viz"
Requires-Dist: tqdm (>=4.66.2,<5.0.0) ; extra == "network"
Requires-Dist: xarray (>=2022.6.0)
Project-URL: Documentation, https://elphick.github.io/mass-composition
Project-URL: Repository, https://github.com/elphick/mass-composition
